mcp_grep/__init__.py
mcp_grep/core.py
mcp_grep/inspector.py
mcp_grep/server.py
mcp_grep-0.2.1.dist-info/licenses/LICENSE
mcp_grep-0.2.1.dist-info/METADATA
mcp_grep-0.2.1.dist-info/WHEEL
mcp_grep-0.2.1.dist-info/entry_points.txt
mcp_grep-0.2.1.dist-info/top_level.txt
mcp_grep-0.2.1.dist-info/RECORD
