Metadata-Version: 2.4
Name: mcp-grep
Version: 0.2.1
Summary: MCP Grep Server
Author-email: Ernie Brodeur <ebrodeur@ujami.net>
License: GPL 3.0+
Requires-Python: >=3.8
License-File: LICENSE
Requires-Dist: mcp
Provides-Extra: dev
Requires-Dist: pytest>=7.0.0; extra == "dev"
Requires-Dist: pytest-bdd>=6.1.0; extra == "dev"
Requires-Dist: black>=23.0.0; extra == "dev"
Requires-Dist: isort>=5.0.0; extra == "dev"
Dynamic: license-file
